easy_choices/__init__.py
easy_choices/choices.py
easy_choices/exceptions.py
easy_choices-1.0.0.dist-info/LICENSE
easy_choices-1.0.0.dist-info/METADATA
easy_choices-1.0.0.dist-info/WHEEL
easy_choices-1.0.0.dist-info/top_level.txt
easy_choices-1.0.0.dist-info/RECORD
