Metadata-Version: 2.1
Name: easy-choices
Version: 1.0.0
Summary: Handle choices field easily
Home-page: https://github.com/olist/easy-choices
Author: Olist Developers
Author-email: developers@olist.com
License: Apache License
Platform: UNKNOWN
Classifier: Development Status :: 5 - Production/Stable  
Classifier: Programming Language :: Python :: 3.6
Classifier: Programming Language :: Python :: 3.7
Classifier: License :: OSI Approved :: Apache Software License
Classifier: Operating System :: OS Independent
Provides-Extra: dev
Requires-Dist: black ; extra == 'dev'
Requires-Dist: isort ; extra == 'dev'
Requires-Dist: pre-commit ; extra == 'dev'
Requires-Dist: pytest ; extra == 'dev'
Requires-Dist: pytest-cov ; extra == 'dev'
Requires-Dist: tox ; extra == 'dev'
